tencentcloud_manager/__init__.py
tencentcloud_manager/tencentcloud_manager.py
tencentcloud_manager/agents/__init__.py
tencentcloud_manager/agents/cam_agent.py
tencentcloud_manager/agents/cvm_agent.py
tencentcloud_manager/agents/tdmq_agent.py
tencentcloud_manager/managers/__init__.py
tencentcloud_manager/managers/cam_manager.py
tencentcloud_manager/managers/cvm_manager.py
tencentcloud_manager/managers/tdmq_manager.py
tencentcloud_manager-0.0.6.dist-info/LICENSE
tencentcloud_manager-0.0.6.dist-info/METADATA
tencentcloud_manager-0.0.6.dist-info/WHEEL
tencentcloud_manager-0.0.6.dist-info/top_level.txt
tencentcloud_manager-0.0.6.dist-info/RECORD
