Metadata-Version: 2.1
Name: tencentcloud-manager
Version: 0.0.6
Summary: A package for calling tencentcloud api.
Home-page: https://gitee.com
Author: ZQX
Author-email: 262293446@qq.com
Classifier: Programming Language :: Python :: 3
Classifier: License :: OSI Approved :: MIT License
Classifier: Operating System :: OS Independent
License-File: LICENSE
